devcontainers4all/__init__.py
devcontainers4all/cli.py
devcontainers4all/docker.py
devcontainers4all/factories.py
devcontainers4all/interfaces.py
devcontainers4all/utils.py
devcontainers4all/vsc.py
devcontainers4all-0.1.0.dist-info/entry_points.txt
devcontainers4all-0.1.0.dist-info/WHEEL
devcontainers4all-0.1.0.dist-info/METADATA
devcontainers4all-0.1.0.dist-info/RECORD
