Metadata-Version: 2.1
Name: devcontainers4all
Version: 0.1.0
Summary: 
Author: Cosimo Alfarano
Author-email: cosimo@alfarano.net
Requires-Python: >=3.9,<4.0
Classifier: Programming Language :: Python :: 3
Classifier: Programming Language :: Python :: 3.9
Classifier: Programming Language :: Python :: 3.10
Requires-Dist: behave (>=1.2.6,<2.0.0)
Requires-Dist: click (>=8.0.3,<9.0.0)
Requires-Dist: click-pathlib (>=2020.3.13.0,<2021.0.0.0)
Requires-Dist: commentjson (>=0.9.0,<0.10.0)
Requires-Dist: docker (>=5.0.3,<6.0.0)
Requires-Dist: logzero (>=1.7.0,<2.0.0)
Requires-Dist: pexpect (>=4.8.0,<5.0.0)
